qsearch/__init__.py
qsearch/advanced_unitaries.py
qsearch/assemblers.py
qsearch/backends.py
qsearch/checkpoints.py
qsearch/comparison.py
qsearch/compiler.py
qsearch/defaults.py
qsearch/evaluation.py
qsearch/gates.py
qsearch/gatesets.py
qsearch/heuristics.py
qsearch/integrations.py
qsearch/leap_compiler.py
qsearch/logging.py
qsearch/multistart_solvers.py
qsearch/objectives.py
qsearch/options.py
qsearch/parallelizers.py
qsearch/persistent_aposmm.py
qsearch/post_processing.py
qsearch/project.py
qsearch/solvers.py
qsearch/unitaries.py
qsearch/utils.py
qsearch-2.6.0.dist-info/LICENSE
qsearch-2.6.0.dist-info/METADATA
qsearch-2.6.0.dist-info/WHEEL
qsearch-2.6.0.dist-info/top_level.txt
qsearch-2.6.0.dist-info/RECORD
