Metadata-Version: 2.1
Name: qsearch
Version: 2.6.0
Summary: Search-Based Quantum Synthesis/Compilation
Home-page: https://github.com/BQSKit/qsearch
Author: LBNL - AQT
Author-email: marc.davis@berkeley.edu
License: UNKNOWN
Keywords: quantum compilers synthesis computing
Platform: UNKNOWN
Classifier: Development Status :: 5 - Production/Stable
Classifier: Intended Audience :: Science/Research
Classifier: Topic :: Software Development :: Compilers
Classifier: Programming Language :: Python :: 3.7
Classifier: Programming Language :: Python :: 3.8
Classifier: Programming Language :: Python :: 3.9
Requires-Python: <4,>3.6
License-File: LICENSE
Requires-Dist: numpy (>=1.16.5)
Requires-Dist: scipy
Requires-Dist: qsrs (<3.0.0,>=2.0.0)
Provides-Extra: cma
Requires-Dist: cma ; extra == 'cma'
